convertsize/__init__.py
convertsize/convertsize.py
convertsize-0.1.0.dist-info/LICENSE.md
convertsize-0.1.0.dist-info/METADATA
convertsize-0.1.0.dist-info/WHEEL
convertsize-0.1.0.dist-info/top_level.txt
convertsize-0.1.0.dist-info/RECORD
