Metadata-Version: 2.1
Name: convertsize
Version: 0.1.0
Summary: Convert one file size type to another
Home-page: https://github.com/DevelopersToolbox/convert-size
Author: Wolf Software
Author-email: <pypi@wolfsoftware.com>
License: MIT
Project-URL: Source, https://github.com/DevelopersToolbox/convert-size
Project-URL: Tracker, https://github.com/DevelopersToolbox/convert-size/issues/
Project-URL: Documentation, https://github.com/DevelopersToolbox/convert-size
Project-URL: Funding, https://ko-fi.com/wolfsoftware
Project-URL: Say Thanks!, https://saythanks.io/to/TGWolf
Keywords: python,convert_size
Classifier: Development Status :: 4 - Beta
Classifier: Environment :: Console
Classifier: Intended Audience :: End Users/Desktop
Classifier: Intended Audience :: Developers
Classifier: Intended Audience :: System Administrators
Classifier: License :: OSI Approved :: MIT License
Classifier: Programming Language :: Python :: 3
Classifier: Programming Language :: Python :: 3.7
Classifier: Programming Language :: Python :: 3.8
Classifier: Programming Language :: Python :: 3.9
Classifier: Programming Language :: Python :: 3.10
Classifier: Operating System :: MacOS :: MacOS X
Classifier: Operating System :: Microsoft :: Windows
Classifier: Operating System :: POSIX
Classifier: Topic :: Software Development
License-File: LICENSE.md
